MANIFEST.in
README.rst
requirements.txt
setup.py
slackpy/__init__.py
slackpy/commandline.py
slackpy/slackpy.py
slackpy.egg-info/PKG-INFO
slackpy.egg-info/SOURCES.txt
slackpy.egg-info/dependency_links.txt
slackpy.egg-info/entry_points.txt
slackpy.egg-info/requires.txt
slackpy.egg-info/top_level.txt