Metadata-Version: 1.1
Name: slackpy
Version: 2.2.2
Summary: A Simple and Human Friendly Slack Client for Logging.
Home-page: https://github.com/iktakahiro/slackpy
Author: Takahiro Ikeuchi
Author-email: takahiro.ikeuchi@gmail.com
License: MIT
Keywords: Slack,Slack Client
Platform: UNKNOWN
Classifier: License :: OSI Approved :: MIT License
Classifier: Programming Language :: Python :: 3.5
Classifier: Programming Language :: Python :: 3.4
Classifier: Programming Language :: Python :: 2.7
Classifier: Topic :: System :: Logging
Classifier: Topic :: Communications :: Chat
